README.md
setup.py
rslib/__init__.py
rslib.egg-info/PKG-INFO
rslib.egg-info/SOURCES.txt
rslib.egg-info/dependency_links.txt
rslib.egg-info/top_level.txt
rslib/algo/__init__.py
rslib/algo/keras_models/__init__.py
rslib/algo/keras_models/han.py
rslib/algo/pytorch/__init__.py
rslib/algo/pytorch/base/__init__.py
rslib/algo/pytorch/sparse/__init__.py
rslib/algo/pytorch/sparse/sparse_linear.py
rslib/algo/pytorch/transformer/__init__.py
rslib/algo/pytorch/transformer/transformer.py
rslib/algo/tensorflow/__init__.py
rslib/algo/tensorflow/CNN/__init__.py
rslib/algo/tensorflow/CNN/sepCNN.py
rslib/algo/tensorflow/CNN/sepCNNLayer.py
rslib/algo/tensorflow/atrank/ATRank.py
rslib/algo/tensorflow/atrank/ATRankLayer.py
rslib/algo/tensorflow/atrank/ATRankforPM02.py
rslib/algo/tensorflow/atrank/ATRankforQier.py
rslib/algo/tensorflow/atrank/ATRankforRL.py
rslib/algo/tensorflow/atrank/ATRankforRL3.py
rslib/algo/tensorflow/atrank/BaseforRL.py
rslib/algo/tensorflow/atrank/__init__.py
rslib/algo/tensorflow/atrank/contrib.py
rslib/algo/tensorflow/attention/Attention.py
rslib/algo/tensorflow/attention/AttentionLayer.py
rslib/algo/tensorflow/attention/__init__.py
rslib/algo/tensorflow/conv_transformer/ConvTransformerLayer.py
rslib/algo/tensorflow/conv_transformer/ConvTransformer_basic.py
rslib/algo/tensorflow/conv_transformer/__init__.py
rslib/algo/tensorflow/conv_transformer/contrib.py
rslib/algo/tensorflow/dien/DIEN.py
rslib/algo/tensorflow/dien/DIENLayer.py
rslib/algo/tensorflow/dien/Dice.py
rslib/algo/tensorflow/dien/__init__.py
rslib/algo/tensorflow/dien/rnn.py
rslib/algo/tensorflow/dien/utils.py
rslib/algo/tensorflow/din/DIN.py
rslib/algo/tensorflow/din/DINLayer.py
rslib/algo/tensorflow/din/__init__.py
rslib/algo/tensorflow/din/contrib.py
rslib/algo/tensorflow/dsin/DSIN.py
rslib/algo/tensorflow/dsin/DSINLayer.py
rslib/algo/tensorflow/dsin/__init__.py
rslib/algo/tensorflow/layers/__init__.py
rslib/algo/tensorflow/layers/activation.py
rslib/algo/tensorflow/layers/core.py
rslib/algo/tensorflow/layers/input.py
rslib/algo/tensorflow/layers/interaction.py
rslib/algo/tensorflow/layers/normalization.py
