Metadata-Version: 2.1
Name: rslib
Version: 2.3.7
Summary: offline train_env framework in diting group
Home-page: https://gitlab.leihuo.netease.com/userpersona/diting/rslib
Author: wangkai02
Author-email: wangkai02@corp.netease.com
License: MIT
Platform: UNKNOWN
